intrand/__init__.py
intrand/__main__.py
intrand/dict_utils.py
intrand/list_utils.py
intrand-0.0.6.dist-info/LICENSE
intrand-0.0.6.dist-info/METADATA
intrand-0.0.6.dist-info/WHEEL
intrand-0.0.6.dist-info/top_level.txt
intrand-0.0.6.dist-info/RECORD
