Metadata-Version: 2.1
Name: intrand
Version: 0.0.6
Summary: various handy utilities
Home-page: https://github.com/intrand/intrand.py
Author: intrand
Author-email: intrand@intrand.io
License: UNKNOWN
Platform: UNKNOWN
Classifier: Programming Language :: Python :: 3
Classifier: License :: OSI Approved :: MIT License
Classifier: Operating System :: OS Independent
Requires-Python: >=3.7
